LICENSE
setup.py
mkdocs_no_sitemap_plugin/__init__.py
mkdocs_no_sitemap_plugin/plugin.py
mkdocs_no_sitemap_plugin.egg-info/PKG-INFO
mkdocs_no_sitemap_plugin.egg-info/SOURCES.txt
mkdocs_no_sitemap_plugin.egg-info/dependency_links.txt
mkdocs_no_sitemap_plugin.egg-info/entry_points.txt
mkdocs_no_sitemap_plugin.egg-info/top_level.txt