Metadata-Version: 2.4
Name: mkdocs-no-sitemap-plugin
Version: 0.0.2
Summary: Mkdocs plugin disable the generation.
Home-page: https://github.com/leonardehrenfried/mkdocs-no-sitemap-plugin
Author: leonardehrenfried
Author-email: mail@leonard.io
License: MIT
License-File: LICENSE
Dynamic: author
Dynamic: author-email
Dynamic: description
Dynamic: description-content-type
Dynamic: home-page
Dynamic: license
Dynamic: license-file
Dynamic: summary
